hpmiko/__init__.py
hpmiko/hpmiko.py
hpmiko/templates/__init__.py
hpmiko/templates/get_interfaces.textfsm
hpmiko/templates/show_int_transceiver_detail.textfsm
hpmiko/templates/show_lldp_info_re.textfsm
hpmiko/templates/show_lldp_info_re_int.textfsm
hpmiko/templates/show_name.textfsm
hpmiko/templates/show_system.textfsm
hpmiko/templates/show_tech_buffers.textfsm
hpmiko/templates/show_vlan.textfsm
hpmiko/templates/show_vlans.textfsm
HPmiko-1.1.0.dist-info/LICENSE
HPmiko-1.1.0.dist-info/METADATA
HPmiko-1.1.0.dist-info/WHEEL
HPmiko-1.1.0.dist-info/top_level.txt
HPmiko-1.1.0.dist-info/RECORD
