Metadata-Version: 2.1
Name: HPmiko
Version: 1.1.0
Summary: HPmiko is a middle-man script to simplify extracting data from HP/Aruba Procurve switches using Netmiko
Home-page: https://github.com/andytruett/HPmiko
Author: Andy Truett
Author-email: andrew.truett@gmail.com
License: MIT License
Download-URL: https://github.com/andytruett/HPmiko/archive/1.0.0.tar.gz
Keywords: HP Aruba Procurve netmiko
Platform: UNKNOWN
Classifier: Programming Language :: Python :: 3
Classifier: License :: OSI Approved :: MIT License
Classifier: Operating System :: OS Independent
Requires-Dist: netmiko (>=2.4.0)
